bored/__init__.py
bored/bored.py
bored-1.0.1.dist-info/METADATA
bored-1.0.1.dist-info/RECORD
bored-1.0.1.dist-info/WHEEL
bored-1.0.1.dist-info/top_level.txt
