Metadata-Version: 2.1
Name: bored
Version: 1.0.1
Summary: Unofficial Wrapper for Bored API
Home-page: http://henryb.uk
Author: Henry Bersey
Author-email: henry@bersey.com
License: UNKNOWN
Platform: UNKNOWN
Requires-Dist: requests
